streammachine/__init__.py
streammachine/api/__init__.py
streammachine/api/account/__init__.py
streammachine/api/account/v1/__init__.py
streammachine/api/account/v1/account_v1_pb2.py
streammachine/api/account/v1/account_v1_pb2_grpc.py
streammachine/api/batch_exporters/__init__.py
streammachine/api/batch_exporters/v1/__init__.py
streammachine/api/batch_exporters/v1/batch_exporters_v1_pb2.py
streammachine/api/batch_exporters/v1/batch_exporters_v1_pb2_grpc.py
streammachine/api/cli/__init__.py
streammachine/api/cli/v1/__init__.py
streammachine/api/cli/v1/cli_pb2.py
streammachine/api/cli/v1/cli_pb2_grpc.py
streammachine/api/consent_levels/__init__.py
streammachine/api/consent_levels/v1/__init__.py
streammachine/api/consent_levels/v1/consent_levels_v1_pb2.py
streammachine/api/consent_levels/v1/consent_levels_v1_pb2_grpc.py
streammachine/api/credentials/__init__.py
streammachine/api/credentials/v1/__init__.py
streammachine/api/credentials/v1/credentials_v1_pb2.py
streammachine/api/credentials/v1/credentials_v1_pb2_grpc.py
streammachine/api/entities/__init__.py
streammachine/api/entities/v1/__init__.py
streammachine/api/entities/v1/entities_v1_pb2.py
streammachine/api/entities/v1/entities_v1_pb2_grpc.py
streammachine/api/event_contracts/__init__.py
streammachine/api/event_contracts/v1/__init__.py
streammachine/api/event_contracts/v1/event_contracts_v1_pb2.py
streammachine/api/event_contracts/v1/event_contracts_v1_pb2_grpc.py
streammachine/api/kafka_clusters/__init__.py
streammachine/api/kafka_clusters/v1/__init__.py
streammachine/api/kafka_clusters/v1/kafka_clusters_v1_pb2.py
streammachine/api/kafka_clusters/v1/kafka_clusters_v1_pb2_grpc.py
streammachine/api/kafka_exporters/__init__.py
streammachine/api/kafka_exporters/v1/__init__.py
streammachine/api/kafka_exporters/v1/kafka_exporters_v1_pb2.py
streammachine/api/kafka_exporters/v1/kafka_exporters_v1_pb2_grpc.py
streammachine/api/kafka_users/__init__.py
streammachine/api/kafka_users/v1/__init__.py
streammachine_api_definitions-1.31.0.dist-info/METADATA
streammachine_api_definitions-1.31.0.dist-info/WHEEL
streammachine_api_definitions-1.31.0.dist-info/top_level.txt
streammachine_api_definitions-1.31.0.dist-info/RECORD
